{
  "appInfo" : {
    "build" : "242.23726.103.2422.12816248",
    "buildDate" : "2024-12-18T01:33:00Z[UTC]",
    "productCode" : "AI",
    "generated" : "2025-02-12T16:34:49.911825Z",
    "os" : "macOS 15.3",
    "runtime" : "JetBrains s.r.o. 21.0.4 21.0.4+-12422083-b607.1"
  },
  "runtimeInfo" : {
    "maxMemory" : 2147483648,
    "numberOfProcessors" : 32,
    "maxNumberOfIndexingThreads" : 31,
    "maxSizeOfFileForIntelliSense" : 2560000,
    "maxSizeOfFileForContentLoading" : 20971520
  },
  "type" : "Scanning",
  "projectIndexingActivityHistory" : {
    "projectName" : "untitled",
    "times" : {
      "scanningReason" : "On project open",
      "scanningType" : "FULL_ON_PROJECT_OPEN",
      "scanningId" : 0,
      "creatingIteratorsTime" : 0,
      "concurrentHandlingWallTimeWithoutPauses" : 0,
      "concurrentHandlingWallTimeWithPauses" : 0,
      "concurrentHandlingSumOfThreadTimesWithPauses" : 3810216522,
      "concurrentIterationAndScannersApplicationSumOfThreadTimesWithPauses" : 364653613,
      "concurrentFileCheckSumOfThreadTimesWithPauses" : 3435737622,
      "delayedPushPropertiesStageTime" : 0,
      "indexExtensionsTime" : 0,
      "dumbWallTimeWithPauses" : 0,
      "dumbWallTimeWithoutPauses" : 0,
      "updatingStart" : "2025-02-12T16:34:47.824645Z",
      "updatingEnd" : "2025-02-12T16:34:49.90918Z",
      "totalWallTimeWithPauses" : 2084500550,
      "wallTimeOnPause" : 1374000,
      "wasInterrupted" : false,
      "totalWallTimeWithoutPauses" : 2083126550
    },
    "fileCount" : {
      "numberOfFileProviders" : 10,
      "numberOfScannedFiles" : 43065,
      "numberOfFilesIndexedByInfrastructureExtensionsDuringScan" : 0,
      "numberOfFilesScheduledForIndexingAfterScan" : 0
    },
    "scanningStatistics" : [ {
      "providerName" : "JDK jbr-17 /Users/jason/Library/Java/JavaVirtualMachines/jbr-17.0.14/Contents/Home",
      "numberOfScannedFiles" : 42840,
      "numberOfSkippedFiles" : 0,
      "numberOfFilesForIndexing" : 0,
      "numberOfFilesFullyIndexedByInfrastructureExtensions" : 0,
      "filesFullyIndexedByInfrastructureExtensions" : [ ],
      "statusTime" : 1171167069,
      "totalOneThreadTimeWithPauses" : 2056583628,
      "iterationAndScannersApplicationTime" : 323640318,
      "filesCheckTime" : 1732439420,
      "timeProcessingUpToDateFiles" : 0,
      "timeUpdatingContentLessIndexes" : 50962500,
      "timeIndexingWithoutContentViaInfrastructureExtension" : 0,
      "roots" : [ ]
    }, {
      "providerName" : "Indexable set contributor 'com.intellij.javaee.ExternalResourcesRootsProvider@5c11c5c4' (non-project)",
      "numberOfScannedFiles" : 210,
      "numberOfSkippedFiles" : 4,
      "numberOfFilesForIndexing" : 0,
      "numberOfFilesFullyIndexedByInfrastructureExtensions" : 0,
      "filesFullyIndexedByInfrastructureExtensions" : [ ],
      "statusTime" : 499971548,
      "totalOneThreadTimeWithPauses" : 1574011713,
      "iterationAndScannersApplicationTime" : 16726754,
      "filesCheckTime" : 1556587739,
      "timeProcessingUpToDateFiles" : 0,
      "timeUpdatingContentLessIndexes" : 571910,
      "timeIndexingWithoutContentViaInfrastructureExtension" : 0,
      "roots" : [ ]
    }, {
      "providerName" : "Module 'untitled' (all roots)",
      "numberOfScannedFiles" : 8,
      "numberOfSkippedFiles" : 0,
      "numberOfFilesForIndexing" : 0,
      "numberOfFilesFullyIndexedByInfrastructureExtensions" : 0,
      "filesFullyIndexedByInfrastructureExtensions" : [ ],
      "statusTime" : 28170242,
      "totalOneThreadTimeWithPauses" : 123396228,
      "iterationAndScannersApplicationTime" : 16757504,
      "filesCheckTime" : 106008724,
      "timeProcessingUpToDateFiles" : 0,
      "timeUpdatingContentLessIndexes" : 16630,
      "timeIndexingWithoutContentViaInfrastructureExtension" : 0,
      "roots" : [ ]
    }, {
      "providerName" : "Indexable set contributor 'org.jetbrains.kotlin.idea.base.indices.contributors.BuiltInsIndexableSetContributor@7e1bff30' (non-project)",
      "numberOfScannedFiles" : 7,
      "numberOfSkippedFiles" : 0,
      "numberOfFilesForIndexing" : 0,
      "numberOfFilesFullyIndexedByInfrastructureExtensions" : 0,
      "filesFullyIndexedByInfrastructureExtensions" : [ ],
      "statusTime" : 14728121,
      "totalOneThreadTimeWithPauses" : 24627289,
      "iterationAndScannersApplicationTime" : 1171221,
      "filesCheckTime" : 22405897,
      "timeProcessingUpToDateFiles" : 0,
      "timeUpdatingContentLessIndexes" : 46480,
      "timeIndexingWithoutContentViaInfrastructureExtension" : 0,
      "roots" : [ ]
    }, {
      "providerName" : "Indexable set contributor 'Version Catalogs' (non-project)",
      "numberOfScannedFiles" : 0,
      "numberOfSkippedFiles" : 0,
      "numberOfFilesForIndexing" : 0,
      "numberOfFilesFullyIndexedByInfrastructureExtensions" : 0,
      "filesFullyIndexedByInfrastructureExtensions" : [ ],
      "statusTime" : 0,
      "totalOneThreadTimeWithPauses" : 5280264,
      "iterationAndScannersApplicationTime" : 1046311,
      "filesCheckTime" : 3036342,
      "timeProcessingUpToDateFiles" : 0,
      "timeUpdatingContentLessIndexes" : 0,
      "timeIndexingWithoutContentViaInfrastructureExtension" : 0,
      "roots" : [ ]
    }, {
      "providerName" : "Indexable set contributor 'Scratches & Consoles' (non-project)",
      "numberOfScannedFiles" : 0,
      "numberOfSkippedFiles" : 0,
      "numberOfFilesForIndexing" : 0,
      "numberOfFilesFullyIndexedByInfrastructureExtensions" : 0,
      "filesFullyIndexedByInfrastructureExtensions" : [ ],
      "statusTime" : 0,
      "totalOneThreadTimeWithPauses" : 5278714,
      "iterationAndScannersApplicationTime" : 1146511,
      "filesCheckTime" : 3078282,
      "timeProcessingUpToDateFiles" : 0,
      "timeUpdatingContentLessIndexes" : 0,
      "timeIndexingWithoutContentViaInfrastructureExtension" : 0,
      "roots" : [ ]
    }, {
      "providerName" : "Indexable set contributor 'Version Catalogs' (project)",
      "numberOfScannedFiles" : 0,
      "numberOfSkippedFiles" : 0,
      "numberOfFilesForIndexing" : 0,
      "numberOfFilesFullyIndexedByInfrastructureExtensions" : 0,
      "filesFullyIndexedByInfrastructureExtensions" : [ ],
      "statusTime" : 0,
      "totalOneThreadTimeWithPauses" : 5274984,
      "iterationAndScannersApplicationTime" : 1015581,
      "filesCheckTime" : 3040192,
      "timeProcessingUpToDateFiles" : 0,
      "timeUpdatingContentLessIndexes" : 0,
      "timeIndexingWithoutContentViaInfrastructureExtension" : 0,
      "roots" : [ ]
    }, {
      "providerName" : "Indexable set contributor 'com.intellij.javaee.ExternalResourcesRootsProvider@5c11c5c4' (project)",
      "numberOfScannedFiles" : 0,
      "numberOfSkippedFiles" : 0,
      "numberOfFilesForIndexing" : 0,
      "numberOfFilesFullyIndexedByInfrastructureExtensions" : 0,
      "filesFullyIndexedByInfrastructureExtensions" : [ ],
      "statusTime" : 0,
      "totalOneThreadTimeWithPauses" : 5273564,
      "iterationAndScannersApplicationTime" : 1020281,
      "filesCheckTime" : 3064772,
      "timeProcessingUpToDateFiles" : 0,
      "timeUpdatingContentLessIndexes" : 0,
      "timeIndexingWithoutContentViaInfrastructureExtension" : 0,
      "roots" : [ ]
    }, {
      "providerName" : "Indexable set contributor 'org.jetbrains.kotlin.idea.base.indices.contributors.BuiltInsIndexableSetContributor@7e1bff30' (project)",
      "numberOfScannedFiles" : 0,
      "numberOfSkippedFiles" : 0,
      "numberOfFilesForIndexing" : 0,
      "numberOfFilesFullyIndexedByInfrastructureExtensions" : 0,
      "filesFullyIndexedByInfrastructureExtensions" : [ ],
      "statusTime" : 0,
      "totalOneThreadTimeWithPauses" : 5246204,
      "iterationAndScannersApplicationTime" : 1120041,
      "filesCheckTime" : 3028842,
      "timeProcessingUpToDateFiles" : 0,
      "timeUpdatingContentLessIndexes" : 0,
      "timeIndexingWithoutContentViaInfrastructureExtension" : 0,
      "roots" : [ ]
    }, {
      "providerName" : "Indexable set contributor 'Scratches & Consoles' (project)",
      "numberOfScannedFiles" : 0,
      "numberOfSkippedFiles" : 0,
      "numberOfFilesForIndexing" : 0,
      "numberOfFilesFullyIndexedByInfrastructureExtensions" : 0,
      "filesFullyIndexedByInfrastructureExtensions" : [ ],
      "statusTime" : 0,
      "totalOneThreadTimeWithPauses" : 5243934,
      "iterationAndScannersApplicationTime" : 1009091,
      "filesCheckTime" : 3047412,
      "timeProcessingUpToDateFiles" : 0,
      "timeUpdatingContentLessIndexes" : 0,
      "timeIndexingWithoutContentViaInfrastructureExtension" : 0,
      "roots" : [ ]
    } ]
  }
}